kubectl_ng/__init__.py
kubectl_ng/_api_resources.py
kubectl_ng/_api_versions.py
kubectl_ng/_config.py
kubectl_ng/_cordon_uncordon.py
kubectl_ng/_create.py
kubectl_ng/_delete.py
kubectl_ng/_exec.py
kubectl_ng/_formatters.py
kubectl_ng/_get.py
kubectl_ng/_typer_utils.py
kubectl_ng/_version.py
kubectl_ng/_wait.py
kubectl_ng/cli.py
kubectl_ng/tests/resources/simple/nginx_pod_service.yaml
kubectl_ng/tests/test_api_versions.py
kubectl_ng/tests/test_cli.py
kubectl_ng/tests/test_create_delete.py
kubectl_ng/tests/test_exec.py
kubectl_ng/tests/test_formatters.py
kubectl_ng/tests/test_kng_api_resources.py
kubectl_ng/tests/test_kng_config.py
kubectl_ng/tests/test_kng_get.py
kubectl_ng/tests/test_version.py
kubectl_ng-0.20.8.dist-info/METADATA
kubectl_ng-0.20.8.dist-info/WHEEL
kubectl_ng-0.20.8.dist-info/entry_points.txt
kubectl_ng-0.20.8.dist-info/RECORD
