Metadata-Version: 2.1
Name: kubectl-ng
Version: 0.20.8
Summary: 
Author: Jacob Tomlinson
Author-email: jacob@tomlinson.email
Requires-Python: >=3.9,<4.0
Classifier: Programming Language :: Python :: 3
Classifier: Programming Language :: Python :: 3.9
Classifier: Programming Language :: Python :: 3.10
Classifier: Programming Language :: Python :: 3.11
Requires-Dist: kr8s (==v0.20.8)
Requires-Dist: rich (>=13.3.2,<14.0.0)
Requires-Dist: typer (>=0.12)
